dreamake/__init__.py
dreamake/canvas.py
dreamake/codekit.py
dreamake/colliders.py
dreamake/gui.py
dreamake/locals.py
dreamake/shapes.py
dreamake/tktools.py
Dreamake-0.0.107.dist-info/LICENSE.txt
Dreamake-0.0.107.dist-info/METADATA
Dreamake-0.0.107.dist-info/WHEEL
Dreamake-0.0.107.dist-info/top_level.txt
Dreamake-0.0.107.dist-info/RECORD
