Metadata-Version: 2.1
Name: Dreamake
Version: 0.0.107
Summary: A pygame based game engine made in python.
Home-page: https://github.com/Boglov/dreamake
Author: Nitebound
Author-email: zvisger@gmail.com
License: MIT
Project-URL: Bug Tracker, https://github.com/Boglov/dreamake/issues
Platform: UNKNOWN
Classifier: Programming Language :: Python :: 3
Classifier: License :: OSI Approved :: MIT License
Classifier: Operating System :: OS Independent
Requires-Python: >=3.6
License-File: LICENSE.txt
Requires-Dist: pygame
